CHANGES.rst
MANIFEST.in
README.rst
setup.cfg
setup.py
src/z3c/__init__.py
src/z3c.formwidget.unit.egg-info/PKG-INFO
src/z3c.formwidget.unit.egg-info/SOURCES.txt
src/z3c.formwidget.unit.egg-info/dependency_links.txt
src/z3c.formwidget.unit.egg-info/entry_points.txt
src/z3c.formwidget.unit.egg-info/namespace_packages.txt
src/z3c.formwidget.unit.egg-info/not-zip-safe
src/z3c.formwidget.unit.egg-info/requires.txt
src/z3c.formwidget.unit.egg-info/top_level.txt
src/z3c/formwidget/__init__.py
src/z3c/formwidget/unit/__init__.py
src/z3c/formwidget/unit/configure.zcml
src/z3c/formwidget/unit/i18n.py
src/z3c/formwidget/unit/interfaces.py
src/z3c/formwidget/unit/pint_units.txt
src/z3c/formwidget/unit/tests.py
src/z3c/formwidget/unit/utils.py
src/z3c/formwidget/unit/widget.py
src/z3c/formwidget/unit/widget.txt
src/z3c/formwidget/unit/locales/z3c.formwidget.unit.pot
src/z3c/formwidget/unit/locales/de/LC_MESSAGES/z3c.formwidget.unit.mo
src/z3c/formwidget/unit/locales/de/LC_MESSAGES/z3c.formwidget.unit.po
src/z3c/formwidget/unit/locales/en/LC_MESSAGES/z3c.formwidget.unit.mo
src/z3c/formwidget/unit/locales/en/LC_MESSAGES/z3c.formwidget.unit.po
src/z3c/formwidget/unit/locales/es/LC_MESSAGES/z3c.formwidget.unit.mo
src/z3c/formwidget/unit/locales/es/LC_MESSAGES/z3c.formwidget.unit.po
src/z3c/formwidget/unit/locales/fr/LC_MESSAGES/z3c.formwidget.unit.mo
src/z3c/formwidget/unit/locales/fr/LC_MESSAGES/z3c.formwidget.unit.po
src/z3c/formwidget/unit/locales/it/LC_MESSAGES/z3c.formwidget.unit.mo
src/z3c/formwidget/unit/locales/it/LC_MESSAGES/z3c.formwidget.unit.po
src/z3c/formwidget/unit/locales/ja/LC_MESSAGES/z3c.formwidget.unit.mo
src/z3c/formwidget/unit/locales/ja/LC_MESSAGES/z3c.formwidget.unit.po
src/z3c/formwidget/unit/locales/pt/LC_MESSAGES/z3c.formwidget.unit.mo
src/z3c/formwidget/unit/locales/pt/LC_MESSAGES/z3c.formwidget.unit.po
src/z3c/formwidget/unit/locales/ru/LC_MESSAGES/z3c.formwidget.unit.mo
src/z3c/formwidget/unit/locales/ru/LC_MESSAGES/z3c.formwidget.unit.po
src/z3c/formwidget/unit/locales/zh/LC_MESSAGES/z3c.formwidget.unit.mo
src/z3c/formwidget/unit/locales/zh/LC_MESSAGES/z3c.formwidget.unit.po
src/z3c/formwidget/unit/templates/display.pt
src/z3c/formwidget/unit/templates/input.pt