Metadata-Version: 1.1
Name: z3c.formwidget.unit
Version: 0.2.4
Summary: A multi unit widget for z3c.form.
Home-page: https://github.com/tmassman/z3c.formwidget.unit
Author: Thomas Massmann
Author-email: thomas.massmann@it-spir.it
License: GPL
Download-URL: http://pypi.python.org/pypi/z3c.formwidget.unit
Keywords: zope zope3 z3c.form
Platform: UNKNOWN
Classifier: Development Status :: 4 - Beta
Classifier: Environment :: Web Environment
Classifier: Framework :: Zope3
Classifier: Intended Audience :: Other Audience
Classifier: License :: OSI Approved :: GNU General Public License (GPL)
Classifier: Natural Language :: English
Classifier: Operating System :: OS Independent
Classifier: Programming Language :: Python
Classifier: Programming Language :: Zope
